[
{"result":1,"cur_unit":"META","fetched_at":"2026-05-20T03:27:32+0900"}
,{"result":1,"cur_unit":"USD","ttb":"1533.11","tts":"1478.89","deal_bas_r":"1,506","bkpr":"1506","yy_efee_r":"0","ten_dd_efee_r":"0","kftc_bkpr":"1506","kftc_deal_bas_r":"1,506","cur_nm":"미국 달러"}
,{"result":1,"cur_unit":"JPY","ttb":"964.71","tts":"930.59","deal_bas_r":"947.65","bkpr":"947","yy_efee_r":"0","ten_dd_efee_r":"0","kftc_bkpr":"947","kftc_deal_bas_r":"947.65","cur_nm":"일본 엔"}
,{"result":1,"cur_unit":"EUR","ttb":"1780.25","tts":"1717.29","deal_bas_r":"1,748.77","bkpr":"1748","yy_efee_r":"0","ten_dd_efee_r":"0","kftc_bkpr":"1748","kftc_deal_bas_r":"1,748.77","cur_nm":"유로"}
,{"result":1,"cur_unit":"GBP","ttb":"2055.75","tts":"1983.05","deal_bas_r":"2,019.40","bkpr":"2019","yy_efee_r":"0","ten_dd_efee_r":"0","kftc_bkpr":"2019","kftc_deal_bas_r":"2,019.40","cur_nm":"영국 파운드"}
,{"result":1,"cur_unit":"CNY","ttb":"224.93","tts":"216.97","deal_bas_r":"220.95","bkpr":"220","yy_efee_r":"0","ten_dd_efee_r":"0","kftc_bkpr":"220","kftc_deal_bas_r":"220.95","cur_nm":"중국 위안"}
,{"result":1,"cur_unit":"AUD","ttb":"1090.57","tts":"1052.01","deal_bas_r":"1,071.29","bkpr":"1071","yy_efee_r":"0","ten_dd_efee_r":"0","kftc_bkpr":"1071","kftc_deal_bas_r":"1,071.29","cur_nm":"호주 달러"}
,{"result":1,"cur_unit":"CAD","ttb":"1114.98","tts":"1075.56","deal_bas_r":"1,095.27","bkpr":"1095","yy_efee_r":"0","ten_dd_efee_r":"0","kftc_bkpr":"1095","kftc_deal_bas_r":"1,095.27","cur_nm":"캐나다 달러"}
,{"result":1,"cur_unit":"CHF","ttb":"1943.96","tts":"1875.22","deal_bas_r":"1,909.59","bkpr":"1909","yy_efee_r":"0","ten_dd_efee_r":"0","kftc_bkpr":"1909","kftc_deal_bas_r":"1,909.59","cur_nm":"스위스 프랑"}
,{"result":1,"cur_unit":"HKD","ttb":"195.73","tts":"188.81","deal_bas_r":"192.27","bkpr":"192","yy_efee_r":"0","ten_dd_efee_r":"0","kftc_bkpr":"192","kftc_deal_bas_r":"192.27","cur_nm":"홍콩 달러"}
,{"result":1,"cur_unit":"THB","ttb":"46.96","tts":"45.30","deal_bas_r":"46.13","bkpr":"46","yy_efee_r":"0","ten_dd_efee_r":"0","kftc_bkpr":"46","kftc_deal_bas_r":"46.13","cur_nm":"태국 바트"}
,{"result":1,"cur_unit":"SGD","ttb":"1196.15","tts":"1153.85","deal_bas_r":"1,175","bkpr":"1175","yy_efee_r":"0","ten_dd_efee_r":"0","kftc_bkpr":"1175","kftc_deal_bas_r":"1,175","cur_nm":"싱가포르 달러"}
,{"result":1,"cur_unit":"NZD","ttb":"895.26","tts":"863.60","deal_bas_r":"879.43","bkpr":"879","yy_efee_r":"0","ten_dd_efee_r":"0","kftc_bkpr":"879","kftc_deal_bas_r":"879.43","cur_nm":"뉴질랜드 달러"}
,{"result":1,"cur_unit":"SEK","ttb":"163.24","tts":"157.46","deal_bas_r":"160.35","bkpr":"160","yy_efee_r":"0","ten_dd_efee_r":"0","kftc_bkpr":"160","kftc_deal_bas_r":"160.35","cur_nm":"스웨덴 크로나"}
,{"result":1,"cur_unit":"NOK","ttb":"165.50","tts":"159.64","deal_bas_r":"162.57","bkpr":"162","yy_efee_r":"0","ten_dd_efee_r":"0","kftc_bkpr":"162","kftc_deal_bas_r":"162.57","cur_nm":"노르웨이 크로네"}
,{"result":1,"cur_unit":"DKK","ttb":"238.24","tts":"229.82","deal_bas_r":"234.03","bkpr":"234","yy_efee_r":"0","ten_dd_efee_r":"0","kftc_bkpr":"234","kftc_deal_bas_r":"234.03","cur_nm":"덴마크 크로네"}
,{"result":1,"cur_unit":"MYR","ttb":"385.45","tts":"371.81","deal_bas_r":"378.63","bkpr":"378","yy_efee_r":"0","ten_dd_efee_r":"0","kftc_bkpr":"378","kftc_deal_bas_r":"378.63","cur_nm":"말레이시아 링깃"}
,{"result":1,"cur_unit":"SAR","ttb":"408.55","tts":"394.11","deal_bas_r":"401.33","bkpr":"401","yy_efee_r":"0","ten_dd_efee_r":"0","kftc_bkpr":"401","kftc_deal_bas_r":"401.33","cur_nm":"사우디 리얄"}
,{"result":1,"cur_unit":"AED","ttb":"417.40","tts":"402.64","deal_bas_r":"410.02","bkpr":"410","yy_efee_r":"0","ten_dd_efee_r":"0","kftc_bkpr":"410","kftc_deal_bas_r":"410.02","cur_nm":"아랍에미리트 디르함"}
,{"result":1,"cur_unit":"KWD","ttb":"4959.91","tts":"4784.51","deal_bas_r":"4,872.21","bkpr":"4872","yy_efee_r":"0","ten_dd_efee_r":"0","kftc_bkpr":"4872","kftc_deal_bas_r":"4,872.21","cur_nm":"쿠웨이트 디나르"}
,{"result":1,"cur_unit":"BHD","ttb":"4065.52","tts":"3921.75","deal_bas_r":"3,993.64","bkpr":"3993","yy_efee_r":"0","ten_dd_efee_r":"0","kftc_bkpr":"3993","kftc_deal_bas_r":"3,993.64","cur_nm":"바레인 디나르"}
,{"result":1,"cur_unit":"IDR","ttb":"8.68","tts":"8.38","deal_bas_r":"8.53","bkpr":"8","yy_efee_r":"0","ten_dd_efee_r":"0","kftc_bkpr":"8","kftc_deal_bas_r":"8.53","cur_nm":"인도네시아 루피아"}
,{"result":1,"cur_unit":"BND","ttb":"1196.15","tts":"1153.85","deal_bas_r":"1,175","bkpr":"1175","yy_efee_r":"0","ten_dd_efee_r":"0","kftc_bkpr":"1175","kftc_deal_bas_r":"1,175","cur_nm":"브루나이 달러"}
,{"result":1,"cur_unit":"KRW","ttb":"1.02","tts":"0.98","deal_bas_r":"1","bkpr":"1","yy_efee_r":"0","ten_dd_efee_r":"0","kftc_bkpr":"1","kftc_deal_bas_r":"1","cur_nm":"한국 원"}
]
