[
{"result":1,"cur_unit":"META","fetched_at":"2026-07-14T20:11:16+0900"}
,{"result":1,"cur_unit":"USD","ttb":"1524.45","tts":"1470.55","deal_bas_r":"1,497.50","bkpr":"1497","yy_efee_r":"0","ten_dd_efee_r":"0","kftc_bkpr":"1497","kftc_deal_bas_r":"1,497.50","cur_nm":"미국 달러"}
,{"result":1,"cur_unit":"JPY","ttb":"939.63","tts":"906.41","deal_bas_r":"923.02","bkpr":"923","yy_efee_r":"0","ten_dd_efee_r":"0","kftc_bkpr":"923","kftc_deal_bas_r":"923.02","cur_nm":"일본 엔"}
,{"result":1,"cur_unit":"EUR","ttb":"1736.81","tts":"1675.39","deal_bas_r":"1,706.10","bkpr":"1706","yy_efee_r":"0","ten_dd_efee_r":"0","kftc_bkpr":"1706","kftc_deal_bas_r":"1,706.10","cur_nm":"유로"}
,{"result":1,"cur_unit":"GBP","ttb":"2038.42","tts":"1966.34","deal_bas_r":"2,002.38","bkpr":"2002","yy_efee_r":"0","ten_dd_efee_r":"0","kftc_bkpr":"2002","kftc_deal_bas_r":"2,002.38","cur_nm":"영국 파운드"}
,{"result":1,"cur_unit":"CNY","ttb":"224.77","tts":"216.82","deal_bas_r":"220.80","bkpr":"220","yy_efee_r":"0","ten_dd_efee_r":"0","kftc_bkpr":"220","kftc_deal_bas_r":"220.80","cur_nm":"중국 위안"}
,{"result":1,"cur_unit":"AUD","ttb":"1057.90","tts":"1020.48","deal_bas_r":"1,039.19","bkpr":"1039","yy_efee_r":"0","ten_dd_efee_r":"0","kftc_bkpr":"1039","kftc_deal_bas_r":"1,039.19","cur_nm":"호주 달러"}
,{"result":1,"cur_unit":"CAD","ttb":"1080.44","tts":"1042.23","deal_bas_r":"1,061.34","bkpr":"1061","yy_efee_r":"0","ten_dd_efee_r":"0","kftc_bkpr":"1061","kftc_deal_bas_r":"1,061.34","cur_nm":"캐나다 달러"}
,{"result":1,"cur_unit":"CHF","ttb":"1875.56","tts":"1809.24","deal_bas_r":"1,842.40","bkpr":"1842","yy_efee_r":"0","ten_dd_efee_r":"0","kftc_bkpr":"1842","kftc_deal_bas_r":"1,842.40","cur_nm":"스위스 프랑"}
,{"result":1,"cur_unit":"HKD","ttb":"194.51","tts":"187.63","deal_bas_r":"191.07","bkpr":"191","yy_efee_r":"0","ten_dd_efee_r":"0","kftc_bkpr":"191","kftc_deal_bas_r":"191.07","cur_nm":"홍콩 달러"}
,{"result":1,"cur_unit":"THB","ttb":"45.45","tts":"43.85","deal_bas_r":"44.65","bkpr":"44","yy_efee_r":"0","ten_dd_efee_r":"0","kftc_bkpr":"44","kftc_deal_bas_r":"44.65","cur_nm":"태국 바트"}
,{"result":1,"cur_unit":"SGD","ttb":"1178.78","tts":"1137.10","deal_bas_r":"1,157.94","bkpr":"1157","yy_efee_r":"0","ten_dd_efee_r":"0","kftc_bkpr":"1157","kftc_deal_bas_r":"1,157.94","cur_nm":"싱가포르 달러"}
,{"result":1,"cur_unit":"NZD","ttb":"883.72","tts":"852.47","deal_bas_r":"868.10","bkpr":"868","yy_efee_r":"0","ten_dd_efee_r":"0","kftc_bkpr":"868","kftc_deal_bas_r":"868.10","cur_nm":"뉴질랜드 달러"}
,{"result":1,"cur_unit":"SEK","ttb":"157.28","tts":"151.72","deal_bas_r":"154.50","bkpr":"154","yy_efee_r":"0","ten_dd_efee_r":"0","kftc_bkpr":"154","kftc_deal_bas_r":"154.50","cur_nm":"스웨덴 크로나"}
,{"result":1,"cur_unit":"NOK","ttb":"156.71","tts":"151.17","deal_bas_r":"153.94","bkpr":"153","yy_efee_r":"0","ten_dd_efee_r":"0","kftc_bkpr":"153","kftc_deal_bas_r":"153.94","cur_nm":"노르웨이 크로네"}
,{"result":1,"cur_unit":"DKK","ttb":"232.34","tts":"224.12","deal_bas_r":"228.23","bkpr":"228","yy_efee_r":"0","ten_dd_efee_r":"0","kftc_bkpr":"228","kftc_deal_bas_r":"228.23","cur_nm":"덴마크 크로네"}
,{"result":1,"cur_unit":"MYR","ttb":"373.82","tts":"360.60","deal_bas_r":"367.21","bkpr":"367","yy_efee_r":"0","ten_dd_efee_r":"0","kftc_bkpr":"367","kftc_deal_bas_r":"367.21","cur_nm":"말레이시아 링깃"}
,{"result":1,"cur_unit":"SAR","ttb":"405.89","tts":"391.53","deal_bas_r":"398.71","bkpr":"398","yy_efee_r":"0","ten_dd_efee_r":"0","kftc_bkpr":"398","kftc_deal_bas_r":"398.71","cur_nm":"사우디 리얄"}
,{"result":1,"cur_unit":"AED","ttb":"415.09","tts":"400.41","deal_bas_r":"407.75","bkpr":"407","yy_efee_r":"0","ten_dd_efee_r":"0","kftc_bkpr":"407","kftc_deal_bas_r":"407.75","cur_nm":"아랍에미리트 디르함"}
,{"result":1,"cur_unit":"KWD","ttb":"4920.14","tts":"4746.14","deal_bas_r":"4,833.14","bkpr":"4833","yy_efee_r":"0","ten_dd_efee_r":"0","kftc_bkpr":"4833","kftc_deal_bas_r":"4,833.14","cur_nm":"쿠웨이트 디나르"}
,{"result":1,"cur_unit":"BHD","ttb":"4042.79","tts":"3899.83","deal_bas_r":"3,971.31","bkpr":"3971","yy_efee_r":"0","ten_dd_efee_r":"0","kftc_bkpr":"3971","kftc_deal_bas_r":"3,971.31","cur_nm":"바레인 디나르"}
,{"result":1,"cur_unit":"IDR","ttb":"8.45","tts":"8.15","deal_bas_r":"8.30","bkpr":"8","yy_efee_r":"0","ten_dd_efee_r":"0","kftc_bkpr":"8","kftc_deal_bas_r":"8.30","cur_nm":"인도네시아 루피아"}
,{"result":1,"cur_unit":"BND","ttb":"1178.78","tts":"1137.10","deal_bas_r":"1,157.94","bkpr":"1157","yy_efee_r":"0","ten_dd_efee_r":"0","kftc_bkpr":"1157","kftc_deal_bas_r":"1,157.94","cur_nm":"브루나이 달러"}
,{"result":1,"cur_unit":"KRW","ttb":"1.02","tts":"0.98","deal_bas_r":"1","bkpr":"1","yy_efee_r":"0","ten_dd_efee_r":"0","kftc_bkpr":"1","kftc_deal_bas_r":"1","cur_nm":"한국 원"}
]
