[
{"result":1,"cur_unit":"USD","ttb":"1467.55","tts":"1415.65","deal_bas_r":"1,441.60","bkpr":"1441","yy_efee_r":"0","ten_dd_efee_r":"0","kftc_bkpr":"1441","kftc_deal_bas_r":"1,441.60","cur_nm":"미국 달러"}
,
{"result":1,"cur_unit":"JPY","ttb":"952.77","tts":"919.07","deal_bas_r":"935.92","bkpr":"935","yy_efee_r":"0","ten_dd_efee_r":"0","kftc_bkpr":"935","kftc_deal_bas_r":"935.92","cur_nm":"일본 엔"}
,
{"result":1,"cur_unit":"EUR","ttb":"1751.38","tts":"1689.44","deal_bas_r":"1,720.41","bkpr":"1720","yy_efee_r":"0","ten_dd_efee_r":"0","kftc_bkpr":"1720","kftc_deal_bas_r":"1,720.41","cur_nm":"유로"}
,
{"result":1,"cur_unit":"GBP","ttb":"2019.50","tts":"1948.08","deal_bas_r":"1,983.79","bkpr":"1983","yy_efee_r":"0","ten_dd_efee_r":"0","kftc_bkpr":"1983","kftc_deal_bas_r":"1,983.79","cur_nm":"영국 파운드"}
,
{"result":1,"cur_unit":"CNY","ttb":"211.12","tts":"203.66","deal_bas_r":"207.39","bkpr":"207","yy_efee_r":"0","ten_dd_efee_r":"0","kftc_bkpr":"207","kftc_deal_bas_r":"207.39","cur_nm":"중국 위안"}
,
{"result":1,"cur_unit":"AUD","ttb":"1028.54","tts":"992.16","deal_bas_r":"1,010.35","bkpr":"1010","yy_efee_r":"0","ten_dd_efee_r":"0","kftc_bkpr":"1010","kftc_deal_bas_r":"1,010.35","cur_nm":"호주 달러"}
,
{"result":1,"cur_unit":"CAD","ttb":"1084.98","tts":"1046.61","deal_bas_r":"1,065.80","bkpr":"1065","yy_efee_r":"0","ten_dd_efee_r":"0","kftc_bkpr":"1065","kftc_deal_bas_r":"1,065.80","cur_nm":"캐나다 달러"}
,
{"result":1,"cur_unit":"CHF","ttb":"1909.88","tts":"1842.34","deal_bas_r":"1,876.11","bkpr":"1876","yy_efee_r":"0","ten_dd_efee_r":"0","kftc_bkpr":"1876","kftc_deal_bas_r":"1,876.11","cur_nm":"스위스 프랑"}
,
{"result":1,"cur_unit":"HKD","ttb":"187.96","tts":"181.32","deal_bas_r":"184.64","bkpr":"184","yy_efee_r":"0","ten_dd_efee_r":"0","kftc_bkpr":"184","kftc_deal_bas_r":"184.64","cur_nm":"홍콩 달러"}
,
{"result":1,"cur_unit":"THB","ttb":"46.78","tts":"45.12","deal_bas_r":"45.95","bkpr":"45","yy_efee_r":"0","ten_dd_efee_r":"0","kftc_bkpr":"45","kftc_deal_bas_r":"45.95","cur_nm":"태국 바트"}
,
{"result":1,"cur_unit":"SGD","ttb":"1158.02","tts":"1117.06","deal_bas_r":"1,137.54","bkpr":"1137","yy_efee_r":"0","ten_dd_efee_r":"0","kftc_bkpr":"1137","kftc_deal_bas_r":"1,137.54","cur_nm":"싱가포르 달러"}
,
{"result":1,"cur_unit":"NZD","ttb":"889.11","tts":"857.67","deal_bas_r":"873.39","bkpr":"873","yy_efee_r":"0","ten_dd_efee_r":"0","kftc_bkpr":"873","kftc_deal_bas_r":"873.39","cur_nm":"뉴질랜드 달러"}
,
{"result":1,"cur_unit":"SEK","ttb":"166.01","tts":"160.14","deal_bas_r":"163.08","bkpr":"163","yy_efee_r":"0","ten_dd_efee_r":"0","kftc_bkpr":"163","kftc_deal_bas_r":"163.08","cur_nm":"스웨덴 크로나"}
,
{"result":1,"cur_unit":"NOK","ttb":"153.24","tts":"147.82","deal_bas_r":"150.53","bkpr":"150","yy_efee_r":"0","ten_dd_efee_r":"0","kftc_bkpr":"150","kftc_deal_bas_r":"150.53","cur_nm":"노르웨이 크로네"}
,
{"result":1,"cur_unit":"DKK","ttb":"234.54","tts":"226.24","deal_bas_r":"230.39","bkpr":"230","yy_efee_r":"0","ten_dd_efee_r":"0","kftc_bkpr":"230","kftc_deal_bas_r":"230.39","cur_nm":"덴마크 크로네"}
,
{"result":1,"cur_unit":"MYR","ttb":"372.28","tts":"359.12","deal_bas_r":"365.70","bkpr":"365","yy_efee_r":"0","ten_dd_efee_r":"0","kftc_bkpr":"365","kftc_deal_bas_r":"365.70","cur_nm":"말레이시아 링깃"}
,
{"result":1,"cur_unit":"SAR","ttb":"391.27","tts":"377.43","deal_bas_r":"384.35","bkpr":"384","yy_efee_r":"0","ten_dd_efee_r":"0","kftc_bkpr":"384","kftc_deal_bas_r":"384.35","cur_nm":"사우디 리얄"}
,
{"result":1,"cur_unit":"AED","ttb":"399.60","tts":"385.46","deal_bas_r":"392.53","bkpr":"392","yy_efee_r":"0","ten_dd_efee_r":"0","kftc_bkpr":"392","kftc_deal_bas_r":"392.53","cur_nm":"아랍에미리트 디르함"}
,
{"result":1,"cur_unit":"KWD","ttb":"4815.58","tts":"4645.28","deal_bas_r":"4,730.43","bkpr":"4730","yy_efee_r":"0","ten_dd_efee_r":"0","kftc_bkpr":"4730","kftc_deal_bas_r":"4,730.43","cur_nm":"쿠웨이트 디나르"}
,
{"result":1,"cur_unit":"BHD","ttb":"3892.60","tts":"3754.94","deal_bas_r":"3,823.77","bkpr":"3823","yy_efee_r":"0","ten_dd_efee_r":"0","kftc_bkpr":"3823","kftc_deal_bas_r":"3,823.77","cur_nm":"바레인 디나르"}
,
{"result":1,"cur_unit":"IDR","ttb":"8.76","tts":"8.45","deal_bas_r":"8.61","bkpr":"8","yy_efee_r":"0","ten_dd_efee_r":"0","kftc_bkpr":"8","kftc_deal_bas_r":"8.61","cur_nm":"인도네시아 루피아"}
,
{"result":1,"cur_unit":"BND","ttb":"1158.02","tts":"1117.06","deal_bas_r":"1,137.54","bkpr":"1137","yy_efee_r":"0","ten_dd_efee_r":"0","kftc_bkpr":"1137","kftc_deal_bas_r":"1,137.54","cur_nm":"브루나이 달러"}
,
{"result":1,"cur_unit":"KRW","ttb":"1.02","tts":"0.98","deal_bas_r":"1","bkpr":"1","yy_efee_r":"0","ten_dd_efee_r":"0","kftc_bkpr":"1","kftc_deal_bas_r":"1","cur_nm":"한국 원"}
]
