[
{"result":1,"cur_unit":"USD","ttb":"1397.38","tts":"1425.61","deal_bas_r":"1,411.50","bkpr":"1411","yy_efee_r":"0","ten_dd_efee_r":"0","kftc_bkpr":"1411","kftc_deal_bas_r":"1,411.50","cur_nm":"미국 달러"}
,
{"result":1,"cur_unit":"JPY","ttb":"932.30","tts":"951.13","deal_bas_r":"941.72","bkpr":"941","yy_efee_r":"0","ten_dd_efee_r":"0","kftc_bkpr":"941","kftc_deal_bas_r":"941.72","cur_nm":"일본 엔"}
,
{"result":1,"cur_unit":"EUR","ttb":"1633.12","tts":"1666.11","deal_bas_r":"1,649.62","bkpr":"1649","yy_efee_r":"0","ten_dd_efee_r":"0","kftc_bkpr":"1649","kftc_deal_bas_r":"1,649.62","cur_nm":"유로"}
,
{"result":1,"cur_unit":"GBP","ttb":"1877.80","tts":"1915.73","deal_bas_r":"1,896.77","bkpr":"1896","yy_efee_r":"0","ten_dd_efee_r":"0","kftc_bkpr":"1896","kftc_deal_bas_r":"1,896.77","cur_nm":"영국 파운드"}
,
{"result":1,"cur_unit":"CNY","ttb":"195.61","tts":"199.56","deal_bas_r":"197.59","bkpr":"197","yy_efee_r":"0","ten_dd_efee_r":"0","kftc_bkpr":"197","kftc_deal_bas_r":"197.59","cur_nm":"중국 위안"}
,
{"result":1,"cur_unit":"AUD","ttb":"923.18","tts":"941.83","deal_bas_r":"932.51","bkpr":"932","yy_efee_r":"0","ten_dd_efee_r":"0","kftc_bkpr":"932","kftc_deal_bas_r":"932.51","cur_nm":"호주 달러"}
,
{"result":1,"cur_unit":"CAD","ttb":"1000.95","tts":"1021.18","deal_bas_r":"1,011.07","bkpr":"1011","yy_efee_r":"0","ten_dd_efee_r":"0","kftc_bkpr":"1011","kftc_deal_bas_r":"1,011.07","cur_nm":"캐나다 달러"}
,
{"result":1,"cur_unit":"CHF","ttb":"1752.42","tts":"1787.83","deal_bas_r":"1,770.13","bkpr":"1770","yy_efee_r":"0","ten_dd_efee_r":"0","kftc_bkpr":"1770","kftc_deal_bas_r":"1,770.13","cur_nm":"스위스 프랑"}
,
{"result":1,"cur_unit":"HKD","ttb":"179.53","tts":"183.16","deal_bas_r":"181.35","bkpr":"181","yy_efee_r":"0","ten_dd_efee_r":"0","kftc_bkpr":"181","kftc_deal_bas_r":"181.35","cur_nm":"홍콩 달러"}
,
{"result":1,"cur_unit":"THB","ttb":"43.08","tts":"43.95","deal_bas_r":"43.52","bkpr":"43","yy_efee_r":"0","ten_dd_efee_r":"0","kftc_bkpr":"43","kftc_deal_bas_r":"43.52","cur_nm":"태국 바트"}
,
{"result":1,"cur_unit":"SGD","ttb":"1080.85","tts":"1102.68","deal_bas_r":"1,091.77","bkpr":"1091","yy_efee_r":"0","ten_dd_efee_r":"0","kftc_bkpr":"1091","kftc_deal_bas_r":"1,091.77","cur_nm":"싱가포르 달러"}
,
{"result":1,"cur_unit":"NZD","ttb":"814.32","tts":"830.77","deal_bas_r":"822.55","bkpr":"822","yy_efee_r":"0","ten_dd_efee_r":"0","kftc_bkpr":"822","kftc_deal_bas_r":"822.55","cur_nm":"뉴질랜드 달러"}
,
{"result":1,"cur_unit":"SEK","ttb":"148.62","tts":"151.63","deal_bas_r":"150.13","bkpr":"150","yy_efee_r":"0","ten_dd_efee_r":"0","kftc_bkpr":"150","kftc_deal_bas_r":"150.13","cur_nm":"스웨덴 크로나"}
,
{"result":1,"cur_unit":"NOK","ttb":"140.44","tts":"143.27","deal_bas_r":"141.86","bkpr":"141","yy_efee_r":"0","ten_dd_efee_r":"0","kftc_bkpr":"141","kftc_deal_bas_r":"141.86","cur_nm":"노르웨이 크로네"}
,
{"result":1,"cur_unit":"DKK","ttb":"218.71","tts":"223.12","deal_bas_r":"220.92","bkpr":"220","yy_efee_r":"0","ten_dd_efee_r":"0","kftc_bkpr":"220","kftc_deal_bas_r":"220.92","cur_nm":"덴마크 크로네"}
,
{"result":1,"cur_unit":"MYR","ttb":"331.53","tts":"338.22","deal_bas_r":"334.88","bkpr":"334","yy_efee_r":"0","ten_dd_efee_r":"0","kftc_bkpr":"334","kftc_deal_bas_r":"334.88","cur_nm":"말레이시아 링깃"}
,
{"result":1,"cur_unit":"SAR","ttb":"372.59","tts":"380.12","deal_bas_r":"376.36","bkpr":"376","yy_efee_r":"0","ten_dd_efee_r":"0","kftc_bkpr":"376","kftc_deal_bas_r":"376.36","cur_nm":"사우디 리얄"}
,
{"result":1,"cur_unit":"AED","ttb":"380.44","tts":"388.13","deal_bas_r":"384.29","bkpr":"384","yy_efee_r":"0","ten_dd_efee_r":"0","kftc_bkpr":"384","kftc_deal_bas_r":"384.29","cur_nm":"아랍에미리트 디르함"}
,
{"result":1,"cur_unit":"KWD","ttb":"4564.07","tts":"4656.28","deal_bas_r":"4,610.18","bkpr":"4610","yy_efee_r":"0","ten_dd_efee_r":"0","kftc_bkpr":"4610","kftc_deal_bas_r":"4,610.18","cur_nm":"쿠웨이트 디나르"}
,
{"result":1,"cur_unit":"BHD","ttb":"3706.78","tts":"3781.67","deal_bas_r":"3,744.23","bkpr":"3744","yy_efee_r":"0","ten_dd_efee_r":"0","kftc_bkpr":"3744","kftc_deal_bas_r":"3,744.23","cur_nm":"바레인 디나르"}
,
{"result":1,"cur_unit":"IDR","ttb":"8.46","tts":"8.63","deal_bas_r":"8.55","bkpr":"8","yy_efee_r":"0","ten_dd_efee_r":"0","kftc_bkpr":"8","kftc_deal_bas_r":"8.55","cur_nm":"인도네시아 루피아"}
,
{"result":1,"cur_unit":"BND","ttb":"1080.85","tts":"1102.68","deal_bas_r":"1,091.77","bkpr":"1091","yy_efee_r":"0","ten_dd_efee_r":"0","kftc_bkpr":"1091","kftc_deal_bas_r":"1,091.77","cur_nm":"브루나이 달러"}
,
{"result":1,"cur_unit":"KRW","ttb":"0.99","tts":"1.01","deal_bas_r":"1","bkpr":"1","yy_efee_r":"0","ten_dd_efee_r":"0","kftc_bkpr":"1","kftc_deal_bas_r":"1","cur_nm":"한국 원"}
]
