[
{"result":1,"cur_unit":"USD","ttb":"1497.89","tts":"1444.91","deal_bas_r":"1,471.40","bkpr":"1471","yy_efee_r":"0","ten_dd_efee_r":"0","kftc_bkpr":"1471","kftc_deal_bas_r":"1,471.40","cur_nm":"미국 달러"}
,
{"result":1,"cur_unit":"JPY","ttb":"958.40","tts":"924.50","deal_bas_r":"941.45","bkpr":"941","yy_efee_r":"0","ten_dd_efee_r":"0","kftc_bkpr":"941","kftc_deal_bas_r":"941.45","cur_nm":"일본 엔"}
,
{"result":1,"cur_unit":"EUR","ttb":"1733.72","tts":"1672.41","deal_bas_r":"1,703.07","bkpr":"1703","yy_efee_r":"0","ten_dd_efee_r":"0","kftc_bkpr":"1703","kftc_deal_bas_r":"1,703.07","cur_nm":"유로"}
,
{"result":1,"cur_unit":"GBP","ttb":"1979.08","tts":"1909.10","deal_bas_r":"1,944.09","bkpr":"1944","yy_efee_r":"0","ten_dd_efee_r":"0","kftc_bkpr":"1944","kftc_deal_bas_r":"1,944.09","cur_nm":"영국 파운드"}
,
{"result":1,"cur_unit":"CNY","ttb":"211.80","tts":"204.31","deal_bas_r":"208.06","bkpr":"208","yy_efee_r":"0","ten_dd_efee_r":"0","kftc_bkpr":"208","kftc_deal_bas_r":"208.06","cur_nm":"중국 위안"}
,
{"result":1,"cur_unit":"AUD","ttb":"977.44","tts":"942.88","deal_bas_r":"960.16","bkpr":"960","yy_efee_r":"0","ten_dd_efee_r":"0","kftc_bkpr":"960","kftc_deal_bas_r":"960.16","cur_nm":"호주 달러"}
,
{"result":1,"cur_unit":"CAD","ttb":"1066.99","tts":"1029.25","deal_bas_r":"1,048.12","bkpr":"1048","yy_efee_r":"0","ten_dd_efee_r":"0","kftc_bkpr":"1048","kftc_deal_bas_r":"1,048.12","cur_nm":"캐나다 달러"}
,
{"result":1,"cur_unit":"CHF","ttb":"1858.99","tts":"1793.25","deal_bas_r":"1,826.12","bkpr":"1826","yy_efee_r":"0","ten_dd_efee_r":"0","kftc_bkpr":"1826","kftc_deal_bas_r":"1,826.12","cur_nm":"스위스 프랑"}
,
{"result":1,"cur_unit":"HKD","ttb":"192.43","tts":"185.63","deal_bas_r":"189.03","bkpr":"189","yy_efee_r":"0","ten_dd_efee_r":"0","kftc_bkpr":"189","kftc_deal_bas_r":"189.03","cur_nm":"홍콩 달러"}
,
{"result":1,"cur_unit":"THB","ttb":"46.52","tts":"44.88","deal_bas_r":"45.70","bkpr":"45","yy_efee_r":"0","ten_dd_efee_r":"0","kftc_bkpr":"45","kftc_deal_bas_r":"45.70","cur_nm":"태국 바트"}
,
{"result":1,"cur_unit":"SGD","ttb":"1154.33","tts":"1113.51","deal_bas_r":"1,133.92","bkpr":"1133","yy_efee_r":"0","ten_dd_efee_r":"0","kftc_bkpr":"1133","kftc_deal_bas_r":"1,133.92","cur_nm":"싱가포르 달러"}
,
{"result":1,"cur_unit":"NZD","ttb":"855.64","tts":"825.38","deal_bas_r":"840.51","bkpr":"840","yy_efee_r":"0","ten_dd_efee_r":"0","kftc_bkpr":"840","kftc_deal_bas_r":"840.51","cur_nm":"뉴질랜드 달러"}
,
{"result":1,"cur_unit":"SEK","ttb":"157.79","tts":"152.21","deal_bas_r":"155","bkpr":"155","yy_efee_r":"0","ten_dd_efee_r":"0","kftc_bkpr":"155","kftc_deal_bas_r":"155","cur_nm":"스웨덴 크로나"}
,
{"result":1,"cur_unit":"NOK","ttb":"147.31","tts":"142.10","deal_bas_r":"144.71","bkpr":"144","yy_efee_r":"0","ten_dd_efee_r":"0","kftc_bkpr":"144","kftc_deal_bas_r":"144.71","cur_nm":"노르웨이 크로네"}
,
{"result":1,"cur_unit":"DKK","ttb":"232.25","tts":"224.03","deal_bas_r":"228.14","bkpr":"228","yy_efee_r":"0","ten_dd_efee_r":"0","kftc_bkpr":"228","kftc_deal_bas_r":"228.14","cur_nm":"덴마크 크로네"}
,
{"result":1,"cur_unit":"MYR","ttb":"362.78","tts":"349.95","deal_bas_r":"356.37","bkpr":"356","yy_efee_r":"0","ten_dd_efee_r":"0","kftc_bkpr":"356","kftc_deal_bas_r":"356.37","cur_nm":"말레이시아 링깃"}
,
{"result":1,"cur_unit":"SAR","ttb":"399.44","tts":"385.32","deal_bas_r":"392.38","bkpr":"392","yy_efee_r":"0","ten_dd_efee_r":"0","kftc_bkpr":"392","kftc_deal_bas_r":"392.38","cur_nm":"사우디 리얄"}
,
{"result":1,"cur_unit":"AED","ttb":"407.99","tts":"393.57","deal_bas_r":"400.78","bkpr":"400","yy_efee_r":"0","ten_dd_efee_r":"0","kftc_bkpr":"400","kftc_deal_bas_r":"400.78","cur_nm":"아랍에미리트 디르함"}
,
{"result":1,"cur_unit":"KWD","ttb":"4879.99","tts":"4707.41","deal_bas_r":"4,793.70","bkpr":"4793","yy_efee_r":"0","ten_dd_efee_r":"0","kftc_bkpr":"4793","kftc_deal_bas_r":"4,793.70","cur_nm":"쿠웨이트 디나르"}
,
{"result":1,"cur_unit":"BHD","ttb":"3974.89","tts":"3834.33","deal_bas_r":"3,904.61","bkpr":"3904","yy_efee_r":"0","ten_dd_efee_r":"0","kftc_bkpr":"3904","kftc_deal_bas_r":"3,904.61","cur_nm":"바레인 디나르"}
,
{"result":1,"cur_unit":"IDR","ttb":"9.02","tts":"8.70","deal_bas_r":"8.86","bkpr":"8","yy_efee_r":"0","ten_dd_efee_r":"0","kftc_bkpr":"8","kftc_deal_bas_r":"8.86","cur_nm":"인도네시아 루피아"}
,
{"result":1,"cur_unit":"BND","ttb":"1154.33","tts":"1113.51","deal_bas_r":"1,133.92","bkpr":"1133","yy_efee_r":"0","ten_dd_efee_r":"0","kftc_bkpr":"1133","kftc_deal_bas_r":"1,133.92","cur_nm":"브루나이 달러"}
,
{"result":1,"cur_unit":"KRW","ttb":"1.02","tts":"0.98","deal_bas_r":"1","bkpr":"1","yy_efee_r":"0","ten_dd_efee_r":"0","kftc_bkpr":"1","kftc_deal_bas_r":"1","cur_nm":"한국 원"}
]
