[
{"result":1,"cur_unit":"USD","ttb":"1494.73","tts":"1441.87","deal_bas_r":"1,468.30","bkpr":"1468","yy_efee_r":"0","ten_dd_efee_r":"0","kftc_bkpr":"1468","kftc_deal_bas_r":"1,468.30","cur_nm":"미국 달러"}
,
{"result":1,"cur_unit":"JPY","ttb":"944.87","tts":"911.45","deal_bas_r":"928.16","bkpr":"928","yy_efee_r":"0","ten_dd_efee_r":"0","kftc_bkpr":"928","kftc_deal_bas_r":"928.16","cur_nm":"일본 엔"}
,
{"result":1,"cur_unit":"EUR","ttb":"1755.41","tts":"1693.33","deal_bas_r":"1,724.37","bkpr":"1724","yy_efee_r":"0","ten_dd_efee_r":"0","kftc_bkpr":"1724","kftc_deal_bas_r":"1,724.37","cur_nm":"유로"}
,
{"result":1,"cur_unit":"GBP","ttb":"2022.30","tts":"1950.78","deal_bas_r":"1,986.54","bkpr":"1986","yy_efee_r":"0","ten_dd_efee_r":"0","kftc_bkpr":"1986","kftc_deal_bas_r":"1,986.54","cur_nm":"영국 파운드"}
,
{"result":1,"cur_unit":"CNY","ttb":"214.75","tts":"207.15","deal_bas_r":"210.95","bkpr":"210","yy_efee_r":"0","ten_dd_efee_r":"0","kftc_bkpr":"210","kftc_deal_bas_r":"210.95","cur_nm":"중국 위안"}
,
{"result":1,"cur_unit":"AUD","ttb":"1025.70","tts":"989.42","deal_bas_r":"1,007.56","bkpr":"1007","yy_efee_r":"0","ten_dd_efee_r":"0","kftc_bkpr":"1007","kftc_deal_bas_r":"1,007.56","cur_nm":"호주 달러"}
,
{"result":1,"cur_unit":"CAD","ttb":"1085.43","tts":"1047.05","deal_bas_r":"1,066.24","bkpr":"1066","yy_efee_r":"0","ten_dd_efee_r":"0","kftc_bkpr":"1066","kftc_deal_bas_r":"1,066.24","cur_nm":"캐나다 달러"}
,
{"result":1,"cur_unit":"CHF","ttb":"1891.57","tts":"1824.67","deal_bas_r":"1,858.12","bkpr":"1858","yy_efee_r":"0","ten_dd_efee_r":"0","kftc_bkpr":"1858","kftc_deal_bas_r":"1,858.12","cur_nm":"스위스 프랑"}
,
{"result":1,"cur_unit":"HKD","ttb":"191.67","tts":"184.89","deal_bas_r":"188.28","bkpr":"188","yy_efee_r":"0","ten_dd_efee_r":"0","kftc_bkpr":"188","kftc_deal_bas_r":"188.28","cur_nm":"홍콩 달러"}
,
{"result":1,"cur_unit":"THB","ttb":"47.99","tts":"46.29","deal_bas_r":"47.14","bkpr":"47","yy_efee_r":"0","ten_dd_efee_r":"0","kftc_bkpr":"47","kftc_deal_bas_r":"47.14","cur_nm":"태국 바트"}
,
{"result":1,"cur_unit":"SGD","ttb":"1168.79","tts":"1127.45","deal_bas_r":"1,148.12","bkpr":"1148","yy_efee_r":"0","ten_dd_efee_r":"0","kftc_bkpr":"1148","kftc_deal_bas_r":"1,148.12","cur_nm":"싱가포르 달러"}
,
{"result":1,"cur_unit":"NZD","ttb":"884.01","tts":"852.75","deal_bas_r":"868.38","bkpr":"868","yy_efee_r":"0","ten_dd_efee_r":"0","kftc_bkpr":"868","kftc_deal_bas_r":"868.38","cur_nm":"뉴질랜드 달러"}
,
{"result":1,"cur_unit":"SEK","ttb":"165.93","tts":"160.07","deal_bas_r":"163","bkpr":"163","yy_efee_r":"0","ten_dd_efee_r":"0","kftc_bkpr":"163","kftc_deal_bas_r":"163","cur_nm":"스웨덴 크로나"}
,
{"result":1,"cur_unit":"NOK","ttb":"152.12","tts":"146.74","deal_bas_r":"149.43","bkpr":"149","yy_efee_r":"0","ten_dd_efee_r":"0","kftc_bkpr":"149","kftc_deal_bas_r":"149.43","cur_nm":"노르웨이 크로네"}
,
{"result":1,"cur_unit":"DKK","ttb":"235.01","tts":"226.69","deal_bas_r":"230.85","bkpr":"230","yy_efee_r":"0","ten_dd_efee_r":"0","kftc_bkpr":"230","kftc_deal_bas_r":"230.85","cur_nm":"덴마크 크로네"}
,
{"result":1,"cur_unit":"MYR","ttb":"373.12","tts":"359.92","deal_bas_r":"366.52","bkpr":"366","yy_efee_r":"0","ten_dd_efee_r":"0","kftc_bkpr":"366","kftc_deal_bas_r":"366.52","cur_nm":"말레이시아 링깃"}
,
{"result":1,"cur_unit":"SAR","ttb":"398.54","tts":"384.44","deal_bas_r":"391.49","bkpr":"391","yy_efee_r":"0","ten_dd_efee_r":"0","kftc_bkpr":"391","kftc_deal_bas_r":"391.49","cur_nm":"사우디 리얄"}
,
{"result":1,"cur_unit":"AED","ttb":"406.89","tts":"392.51","deal_bas_r":"399.70","bkpr":"399","yy_efee_r":"0","ten_dd_efee_r":"0","kftc_bkpr":"399","kftc_deal_bas_r":"399.70","cur_nm":"아랍에미리트 디르함"}
,
{"result":1,"cur_unit":"KWD","ttb":"4889.67","tts":"4716.75","deal_bas_r":"4,803.21","bkpr":"4803","yy_efee_r":"0","ten_dd_efee_r":"0","kftc_bkpr":"4803","kftc_deal_bas_r":"4,803.21","cur_nm":"쿠웨이트 디나르"}
,
{"result":1,"cur_unit":"BHD","ttb":"3963.94","tts":"3823.76","deal_bas_r":"3,893.85","bkpr":"3893","yy_efee_r":"0","ten_dd_efee_r":"0","kftc_bkpr":"3893","kftc_deal_bas_r":"3,893.85","cur_nm":"바레인 디나르"}
,
{"result":1,"cur_unit":"IDR","ttb":"8.91","tts":"8.59","deal_bas_r":"8.75","bkpr":"8","yy_efee_r":"0","ten_dd_efee_r":"0","kftc_bkpr":"8","kftc_deal_bas_r":"8.75","cur_nm":"인도네시아 루피아"}
,
{"result":1,"cur_unit":"BND","ttb":"1168.79","tts":"1127.45","deal_bas_r":"1,148.12","bkpr":"1148","yy_efee_r":"0","ten_dd_efee_r":"0","kftc_bkpr":"1148","kftc_deal_bas_r":"1,148.12","cur_nm":"브루나이 달러"}
,
{"result":1,"cur_unit":"KRW","ttb":"1.02","tts":"0.98","deal_bas_r":"1","bkpr":"1","yy_efee_r":"0","ten_dd_efee_r":"0","kftc_bkpr":"1","kftc_deal_bas_r":"1","cur_nm":"한국 원"}
]
