[
{"result":1,"cur_unit":"USD","ttb":"1458.69","tts":"1407.11","deal_bas_r":"1,432.90","bkpr":"1432","yy_efee_r":"0","ten_dd_efee_r":"0","kftc_bkpr":"1432","kftc_deal_bas_r":"1,432.90","cur_nm":"미국 달러"}
,
{"result":1,"cur_unit":"JPY","ttb":"952.99","tts":"919.29","deal_bas_r":"936.14","bkpr":"936","yy_efee_r":"0","ten_dd_efee_r":"0","kftc_bkpr":"936","kftc_deal_bas_r":"936.14","cur_nm":"일본 엔"}
,
{"result":1,"cur_unit":"EUR","ttb":"1697.33","tts":"1637.31","deal_bas_r":"1,667.32","bkpr":"1667","yy_efee_r":"0","ten_dd_efee_r":"0","kftc_bkpr":"1667","kftc_deal_bas_r":"1,667.32","cur_nm":"유로"}
,
{"result":1,"cur_unit":"GBP","ttb":"1944.58","tts":"1875.82","deal_bas_r":"1,910.20","bkpr":"1910","yy_efee_r":"0","ten_dd_efee_r":"0","kftc_bkpr":"1910","kftc_deal_bas_r":"1,910.20","cur_nm":"영국 파운드"}
,
{"result":1,"cur_unit":"CNY","ttb":"205.22","tts":"197.96","deal_bas_r":"201.59","bkpr":"201","yy_efee_r":"0","ten_dd_efee_r":"0","kftc_bkpr":"201","kftc_deal_bas_r":"201.59","cur_nm":"중국 위안"}
,
{"result":1,"cur_unit":"AUD","ttb":"956.09","tts":"922.28","deal_bas_r":"939.19","bkpr":"939","yy_efee_r":"0","ten_dd_efee_r":"0","kftc_bkpr":"939","kftc_deal_bas_r":"939.19","cur_nm":"호주 달러"}
,
{"result":1,"cur_unit":"CAD","ttb":"1042.11","tts":"1005.25","deal_bas_r":"1,023.68","bkpr":"1023","yy_efee_r":"0","ten_dd_efee_r":"0","kftc_bkpr":"1023","kftc_deal_bas_r":"1,023.68","cur_nm":"캐나다 달러"}
,
{"result":1,"cur_unit":"CHF","ttb":"1832.53","tts":"1767.73","deal_bas_r":"1,800.13","bkpr":"1800","yy_efee_r":"0","ten_dd_efee_r":"0","kftc_bkpr":"1800","kftc_deal_bas_r":"1,800.13","cur_nm":"스위스 프랑"}
,
{"result":1,"cur_unit":"HKD","ttb":"187.80","tts":"181.16","deal_bas_r":"184.48","bkpr":"184","yy_efee_r":"0","ten_dd_efee_r":"0","kftc_bkpr":"184","kftc_deal_bas_r":"184.48","cur_nm":"홍콩 달러"}
,
{"result":1,"cur_unit":"THB","ttb":"44.62","tts":"43.04","deal_bas_r":"43.83","bkpr":"43","yy_efee_r":"0","ten_dd_efee_r":"0","kftc_bkpr":"43","kftc_deal_bas_r":"43.83","cur_nm":"태국 바트"}
,
{"result":1,"cur_unit":"SGD","ttb":"1124.71","tts":"1084.93","deal_bas_r":"1,104.82","bkpr":"1104","yy_efee_r":"0","ten_dd_efee_r":"0","kftc_bkpr":"1104","kftc_deal_bas_r":"1,104.82","cur_nm":"싱가포르 달러"}
,
{"result":1,"cur_unit":"NZD","ttb":"840.57","tts":"810.85","deal_bas_r":"825.71","bkpr":"825","yy_efee_r":"0","ten_dd_efee_r":"0","kftc_bkpr":"825","kftc_deal_bas_r":"825.71","cur_nm":"뉴질랜드 달러"}
,
{"result":1,"cur_unit":"SEK","ttb":"155.34","tts":"149.84","deal_bas_r":"152.59","bkpr":"152","yy_efee_r":"0","ten_dd_efee_r":"0","kftc_bkpr":"152","kftc_deal_bas_r":"152.59","cur_nm":"스웨덴 크로나"}
,
{"result":1,"cur_unit":"NOK","ttb":"146.08","tts":"140.92","deal_bas_r":"143.50","bkpr":"143","yy_efee_r":"0","ten_dd_efee_r":"0","kftc_bkpr":"143","kftc_deal_bas_r":"143.50","cur_nm":"노르웨이 크로네"}
,
{"result":1,"cur_unit":"DKK","ttb":"227.25","tts":"219.21","deal_bas_r":"223.23","bkpr":"223","yy_efee_r":"0","ten_dd_efee_r":"0","kftc_bkpr":"223","kftc_deal_bas_r":"223.23","cur_nm":"덴마크 크로네"}
,
{"result":1,"cur_unit":"MYR","ttb":"346.49","tts":"334.23","deal_bas_r":"340.36","bkpr":"340","yy_efee_r":"0","ten_dd_efee_r":"0","kftc_bkpr":"340","kftc_deal_bas_r":"340.36","cur_nm":"말레이시아 링깃"}
,
{"result":1,"cur_unit":"SAR","ttb":"388.98","tts":"375.22","deal_bas_r":"382.10","bkpr":"382","yy_efee_r":"0","ten_dd_efee_r":"0","kftc_bkpr":"382","kftc_deal_bas_r":"382.10","cur_nm":"사우디 리얄"}
,
{"result":1,"cur_unit":"AED","ttb":"397.14","tts":"383.10","deal_bas_r":"390.12","bkpr":"390","yy_efee_r":"0","ten_dd_efee_r":"0","kftc_bkpr":"390","kftc_deal_bas_r":"390.12","cur_nm":"아랍에미리트 디르함"}
,
{"result":1,"cur_unit":"KWD","ttb":"4756.71","tts":"4588.49","deal_bas_r":"4,672.60","bkpr":"4672","yy_efee_r":"0","ten_dd_efee_r":"0","kftc_bkpr":"4672","kftc_deal_bas_r":"4,672.60","cur_nm":"쿠웨이트 디나르"}
,
{"result":1,"cur_unit":"BHD","ttb":"3869.52","tts":"3732.68","deal_bas_r":"3,801.10","bkpr":"3801","yy_efee_r":"0","ten_dd_efee_r":"0","kftc_bkpr":"3801","kftc_deal_bas_r":"3,801.10","cur_nm":"바레인 디나르"}
,
{"result":1,"cur_unit":"IDR","ttb":"8.80","tts":"8.48","deal_bas_r":"8.64","bkpr":"8","yy_efee_r":"0","ten_dd_efee_r":"0","kftc_bkpr":"8","kftc_deal_bas_r":"8.64","cur_nm":"인도네시아 루피아"}
,
{"result":1,"cur_unit":"BND","ttb":"1124.71","tts":"1084.93","deal_bas_r":"1,104.82","bkpr":"1104","yy_efee_r":"0","ten_dd_efee_r":"0","kftc_bkpr":"1104","kftc_deal_bas_r":"1,104.82","cur_nm":"브루나이 달러"}
,
{"result":1,"cur_unit":"KRW","ttb":"1.02","tts":"0.98","deal_bas_r":"1","bkpr":"1","yy_efee_r":"0","ten_dd_efee_r":"0","kftc_bkpr":"1","kftc_deal_bas_r":"1","cur_nm":"한국 원"}
]
